chatprompt/__init__.py
chatprompt/main.py
chatprompt-3.3.0.dist-info/METADATA
chatprompt-3.3.0.dist-info/WHEEL
chatprompt-3.3.0.dist-info/entry_points.txt
chatprompt-3.3.0.dist-info/top_level.txt
chatprompt-3.3.0.dist-info/RECORD
