Metadata-Version: 2.4
Name: chatprompt
Version: 3.3.0
Summary: A Python package to interact with powerfull AI
Requires-Dist: requests>=2.32.3
Requires-Dist: beautifulsoup4>=4.12.3
Dynamic: description
Dynamic: requires-dist
Dynamic: summary
